django_bootstrap_swt/__init__.py
django_bootstrap_swt/apps.py
django_bootstrap_swt/components.py
django_bootstrap_swt/enums.py
django_bootstrap_swt/utils.py
django_bootstrap_swt/static/django_bootstrap_swt/css/django_bootstrap_swt.css
django_bootstrap_swt/static/django_bootstrap_swt/js/django_bootstrap_swt.js
django_bootstrap_swt/templates/django_bootstrap_swt/components/dropdown.html
django_bootstrap_swt/templates/django_bootstrap_swt/components/modal.html
django_bootstrap_swt/templates/django_bootstrap_swt/components/tag.html
django_bootstrap_swt/templates/django_bootstrap_swt/includes/ajax_error.html
django_bootstrap_swt/templates/django_bootstrap_swt/includes/ajax_loading_spinner.html
django_bootstrap_swt-2.0.1.dist-info/LICENSE
django_bootstrap_swt-2.0.1.dist-info/METADATA
django_bootstrap_swt-2.0.1.dist-info/WHEEL
django_bootstrap_swt-2.0.1.dist-info/top_level.txt
django_bootstrap_swt-2.0.1.dist-info/RECORD
